dott/__init__.py
dott/__version__.py
dott/api.py
dott/runner.py
dott-1.1.1.dist-info/LICENSE
dott-1.1.1.dist-info/METADATA
dott-1.1.1.dist-info/WHEEL
dott-1.1.1.dist-info/top_level.txt
dott-1.1.1.dist-info/RECORD
