Metadata-Version: 2.1
Name: dott
Version: 1.1.1
Summary: A simple scheduling package.
Home-page: https://github.com/alexmacniven/dott
Author: Alex Macniven
Author-email: macniven.ap@gmail.com
License: MIT
Platform: UNKNOWN
Classifier: License :: OSI Approved :: MIT License
Classifier: Programming Language :: Python
Classifier: Programming Language :: Python :: 3
Classifier: Programming Language :: Python :: 3.6
Classifier: Programming Language :: Python :: Implementation :: CPython
Classifier: Programming Language :: Python :: Implementation :: PyPy
Requires-Python: >=3.6.0
